<?xml version="1.0" encoding="UTF-8" ?>
<!DOCTYPE mapper
        PUBLIC "-//mybatis.org//DTD Mapper 3.0//EN"
        "http://mybatis.org/dtd/mybatis-3-mapper.dtd">

<mapper namespace="com.miniproject.cafe.Mapper.MemberMapper">

    <insert id="registerMember" parameterType="MemberVO">
        INSERT INTO member(
        ID,
        EMAIL,
        PASSWORD,
        USERNAME)
        VALUES (
        #{id},
        #{email},
        #{password},
        #{username}
        )
    </insert>

    <select id="loginMember" parameterType="MemberVO" resultType="MemberVO">
        SELECT *
        FROM MEMBER
        WHERE EMAIL = #{email} AND PASSWORD = #{password}
    </select>

    <select id="isEmailDuplicate" parameterType="String" resultType="boolean">
        SELECT COUNT(*) > 0
        FROM MEMBER
        WHERE email = #{email}
    </select>

    <select id="isIdDuplicate" parameterType="String" resultType="boolean">
        SELECT COUNT(*) > 0
        FROM MEMBER
        WHERE ID = #{id}
    </select>
</mapper>